computer_vision_design_patterns/__init__.py
computer_vision_design_patterns/alarm.py
computer_vision_design_patterns/counter.py
computer_vision_design_patterns/event.py
computer_vision_design_patterns/fuzzy.py
computer_vision_design_patterns/pipeline/__init__.py
computer_vision_design_patterns/pipeline/payload.py
computer_vision_design_patterns/pipeline/pipeline.py
computer_vision_design_patterns/pipeline/sample_stage/DummyStage.py
computer_vision_design_patterns/pipeline/sample_stage/RGB2GRAYStage.py
computer_vision_design_patterns/pipeline/sample_stage/SimpleStreamStage.py
computer_vision_design_patterns/pipeline/sample_stage/SwitchStage.py
computer_vision_design_patterns/pipeline/sample_stage/VideoSink.py
computer_vision_design_patterns/pipeline/sample_stage/__init__.py
computer_vision_design_patterns/pipeline/stage.py
computer_vision_design_patterns-2.0.10.dist-info/METADATA
computer_vision_design_patterns-2.0.10.dist-info/WHEEL
computer_vision_design_patterns-2.0.10.dist-info/RECORD
