Metadata-Version: 2.3
Name: computer-vision-design-patterns
Version: 2.0.10
Summary: 
Author: Federico Lanzani
Author-email: hello@federicolanzani.com
Requires-Python: >=3.10,<4.0
Classifier: Programming Language :: Python :: 3
Classifier: Programming Language :: Python :: 3.10
Classifier: Programming Language :: Python :: 3.11
Classifier: Programming Language :: Python :: 3.12
Classifier: Programming Language :: Python :: 3.13
Requires-Dist: loguru (>=0.7.0,<0.8.0)
Requires-Dist: transitions (>=0.9.0,<0.10.0)
